{"GlobalPropertiesHash":"QUelkQzeg4nDN4K6/MsDKCfY62oO/4y0yXezyWymJAg=","FingerprintPatternsHash":"gq3WsqcKBUGTSNle7RKKyXRIwh7M8ccEqOqYvIzoM04=","PropertyOverridesHash":"8ZRc1sGeVrPBx4lD717BgRaQekyh78QKV9SKsdt638U=","InputHashes":["3fuMTLzapfH2M\u002Budp3r0KFPDeIGH1qxDTP1AnFOfhJs=","dm3fPQNTLJNd7AsLDG4G\u002BfHdLpqd0mAI/anQ4yRSHGg=","1QuFPjPZHNnGr8hn/i/dfLcve5M7lyOIqEbMMu6lbhE=","eaW\u002B18RnwH4/H2xOPzFvNwzYY1yN3xom2c1/E7WwCf8=","88v5FRv9H73lY\u002B/j2HXM2mBjyFjhpDrU/Yi1eiepmvc=","\u002BmQ5w\u002BMoE6tVXAjPnUBXnLiAq4nTkcIWi9ajKyF86m4=","5ZvArmXkFHb\u002BVcrsgKNhYblM6D1jlNxoDOPMvMyXMlo=","pClhH5MNBBHyi56KPbc\u002BdHFekLF/KnWrIjcXBLbE724=","XLNBTR/0hC8ZlHHXKvWb6jc1ZEbl2rVWQPrcG2aWmWQ=","IWFTt8tKWtZUZebHoAisEmkTwR9uW84G2FHZR5pYZC4=","cs6JyLI4pdxMgP0oam2IkabpyXkdItxW51bntV0z6Ac=","Z92dQ1U90JZNYW\u002BPiX323NHgAX3gicImS3gkY640nbA=","6xiJtNf\u002BEnaZull9ip/rrDrtrnwM\u002BLEM/PSA81naWls=","ZEEjR5IV8Ox/vKh0wr9ppDk4vN4M\u002BKYoDFDfCnoq6Rk=","qVivQA9kJJqOlWEiocpKxP5b3An\u002BwH5\u002BXGAUoi7zNgM=","ti6e3lwvJqReCSSogjPI4NQUvH9IZUqaj0XQQtxyhDY=","gK9tVigDW17E/Z7n5K9ExM2gVwDH2cSfnrzK8um2xWo=","hSJZfVJjHPh1RloJkFJWDjMpSpLJPgCb2OTppjgK0zk=","4KEp5fnerpD9CXON28nSbnUEKsSAuTNdVRE2b6PmYoY=","Zf3vPOkNu/dVlPJnulMPmShaFoJUiQuqk08mjvo9UMw=","OP9KoH1rjpR0T8HrR2Yb0xK6k7osbs\u002BDmVy5wWc87a8=","P7RPpH/E8D1OPWb3Kl5o0pIAdaCJPPsTm1kTWULr/nw=","f1lp95wqWas4aerBnqSiLgucSEXt87o6wq8ylYCN8qg=","4ui5oV7Ce1NEFovD01wn3pBncacUw2RmtwAaRfS8Pfw=","xTMzJuJajzxnH7NXP\u002BZILXhK3MkHHz3VYP/2xMMARJg=","MRGpdiu6GX8T/iNURFJrlQkv39uEffnfxigUam8m1Q4=","oJFQq6NiaM8JdYrbqrcwS8AI8pZr0K\u002BcetglNTnf9PM=","UqGJjNHIgrYP5cYCYbo\u002BAREecZs3KyowMAPVYEY/kQs=","/kNdB12zDrRlSI4rFzAB\u002BKHD9W\u002BscgsDHKrLrne5wZI=","38EieJ3sMGWpBlTe\u002BLdEXZJiYas3MEd2YYmkqO0CobE="],"CachedAssets":{"3fuMTLzapfH2M\u002Budp3r0KFPDeIGH1qxDTP1AnFOfhJs=":{"Identity":"D:\\saranya\\Job search\\HoneyWell\\VideoMediaApp\\wwwroot\\css\\site.css","SourceId":"VideoMediaApp","SourceType":"Discovered","ContentRoot":"D:\\saranya\\Job search\\HoneyWell\\VideoMediaApp\\wwwroot\\","BasePath":"_content/VideoMediaApp","RelativePath":"css/site#[.{fingerprint}]?.css","AssetKind":"All","AssetMode":"All","AssetRole":"Primary","AssetMergeBehavior":null,"AssetMergeSource":"","RelatedAsset":null,"AssetTraitName":null,"AssetTraitValue":null,"Fingerprint":"bvgxts8hud","Integrity":"WT\u002BqAUcknxGn/qmErI/ZVE6SmVLWLhGWRrWDjPX4w9k=","CopyToOutputDirectory":"Never","CopyToPublishDirectory":"PreserveNewest","OriginalItemSpec":"wwwroot\\css\\site.css","FileLength":8539,"LastWriteTime":"2025-11-23T23:17:28.7790754+00:00"},"dm3fPQNTLJNd7AsLDG4G\u002BfHdLpqd0mAI/anQ4yRSHGg=":{"Identity":"D:\\saranya\\Job search\\HoneyWell\\VideoMediaApp\\wwwroot\\favicon.ico","SourceId":"VideoMediaApp","SourceType":"Discovered","ContentRoot":"D:\\saranya\\Job search\\HoneyWell\\VideoMediaApp\\wwwroot\\","BasePath":"_content/VideoMediaApp","RelativePath":"favicon#[.{fingerprint}]?.ico","AssetKind":"All","AssetMode":"All","AssetRole":"Primary","AssetMergeBehavior":null,"AssetMergeSource":"","RelatedAsset":null,"AssetTraitName":null,"AssetTraitValue":null,"Fingerprint":"61n19gt1b8","Integrity":"Jtxf9L\u002B5ITKRc1gIRl4VbUpGkRNfOBXjYTdhJD4facM=","CopyToOutputDirectory":"Never","CopyToPublishDirectory":"PreserveNewest","OriginalItemSpec":"wwwroot\\favicon.ico","FileLength":5430,"LastWriteTime":"2025-11-21T06:19:07.5508344+00:00"},"1QuFPjPZHNnGr8hn/i/dfLcve5M7lyOIqEbMMu6lbhE=":{"Identity":"D:\\saranya\\Job search\\HoneyWell\\VideoMediaApp\\wwwroot\\js\\site.js","SourceId":"VideoMediaApp","SourceType":"Discovered","ContentRoot":"D:\\saranya\\Job search\\HoneyWell\\VideoMediaApp\\wwwroot\\","BasePath":"_content/VideoMediaApp","RelativePath":"js/site#[.{fingerprint}]?.js","AssetKind":"All","AssetMode":"All","AssetRole":"Primary","AssetMergeBehavior":null,"AssetMergeSource":"","RelatedAsset":null,"AssetTraitName":null,"AssetTraitValue":null,"Fingerprint":"xtxxf3hu2r","Integrity":"hRQyftXiu1lLX2P9Ly9xa4gHJgLeR1uGN5qegUobtGo=","CopyToOutputDirectory":"Never","CopyToPublishDirectory":"PreserveNewest","OriginalItemSpec":"wwwroot\\js\\site.js","FileLength":231,"LastWriteTime":"2025-11-21T06:19:07.1234239+00:00"},"eaW\u002B18RnwH4/H2xOPzFvNwzYY1yN3xom2c1/E7WwCf8=":{"Identity":"D:\\saranya\\Job search\\HoneyWell\\VideoMediaApp\\wwwroot\\js\\upload.js","SourceId":"VideoMediaApp","SourceType":"Discovered","ContentRoot":"D:\\saranya\\Job search\\HoneyWell\\VideoMediaApp\\wwwroot\\","BasePath":"_content/VideoMediaApp","RelativePath":"js/upload#[.{fingerprint}]?.js","AssetKind":"All","AssetMode":"All","AssetRole":"Primary","AssetMergeBehavior":null,"AssetMergeSource":"","RelatedAsset":null,"AssetTraitName":null,"AssetTraitValue":null,"Fingerprint":"fx8qnjkl4m","Integrity":"s9IOZ2yDMZsp\u002B82Ue8ohzy72TMd7lGc3fojnk8q9S\u002Bk=","CopyToOutputDirectory":"Never","CopyToPublishDirectory":"PreserveNewest","OriginalItemSpec":"wwwroot\\js\\upload.js","FileLength":4801,"LastWriteTime":"2025-11-24T01:59:07.2589857+00:00"},"88v5FRv9H73lY\u002B/j2HXM2mBjyFjhpDrU/Yi1eiepmvc=":{"Identity":"D:\\saranya\\Job search\\HoneyWell\\VideoMediaApp\\wwwroot\\js\\video-player.js","SourceId":"VideoMediaApp","SourceType":"Discovered","ContentRoot":"D:\\saranya\\Job search\\HoneyWell\\VideoMediaApp\\wwwroot\\","BasePath":"_content/VideoMediaApp","RelativePath":"js/video-player#[.{fingerprint}]?.js","AssetKind":"All","AssetMode":"All","AssetRole":"Primary","AssetMergeBehavior":null,"AssetMergeSource":"","RelatedAsset":null,"AssetTraitName":null,"AssetTraitValue":null,"Fingerprint":"ns8cawboxg","Integrity":"hzHKOb4k28US0N0cANYhnVdyco6BalloLwoCEKv0AcQ=","CopyToOutputDirectory":"Never","CopyToPublishDirectory":"PreserveNewest","OriginalItemSpec":"wwwroot\\js\\video-player.js","FileLength":1002,"LastWriteTime":"2025-11-23T23:14:41.7048263+00:00"},"\u002BmQ5w\u002BMoE6tVXAjPnUBXnLiAq4nTkcIWi9ajKyF86m4=":{"Identity":"D:\\saranya\\Job search\\HoneyWell\\VideoMediaApp\\wwwroot\\lib\\jquery-validation-unobtrusive\\jquery.validate.unobtrusive.js","SourceId":"VideoMediaApp","SourceType":"Discovered","ContentRoot":"D:\\saranya\\Job search\\HoneyWell\\VideoMediaApp\\wwwroot\\","BasePath":"_content/VideoMediaApp","RelativePath":"lib/jquery-validation-unobtrusive/jquery.validate.unobtrusive#[.{fingerprint}]?.js","AssetKind":"All","AssetMode":"All","AssetRole":"Primary","AssetMergeBehavior":null,"AssetMergeSource":"","RelatedAsset":null,"AssetTraitName":null,"AssetTraitValue":null,"Fingerprint":"47otxtyo56","Integrity":"wJQaJ0XynBE2fq6CexXXhxKu7fstVmQc7V2MHNTo\u002BWQ=","CopyToOutputDirectory":"Never","CopyToPublishDirectory":"PreserveNewest","OriginalItemSpec":"wwwroot\\lib\\jquery-validation-unobtrusive\\jquery.validate.unobtrusive.js","FileLength":19385,"LastWriteTime":"2025-11-21T06:19:08.7343257+00:00"},"5ZvArmXkFHb\u002BVcrsgKNhYblM6D1jlNxoDOPMvMyXMlo=":{"Identity":"D:\\saranya\\Job search\\HoneyWell\\VideoMediaApp\\wwwroot\\lib\\jquery-validation-unobtrusive\\jquery.validate.unobtrusive.min.js","SourceId":"VideoMediaApp","SourceType":"Discovered","ContentRoot":"D:\\saranya\\Job search\\HoneyWell\\VideoMediaApp\\wwwroot\\","BasePath":"_content/VideoMediaApp","RelativePath":"lib/jquery-validation-unobtrusive/jquery.validate.unobtrusive.min#[.{fingerprint}]?.js","AssetKind":"All","AssetMode":"All","AssetRole":"Primary","AssetMergeBehavior":null,"AssetMergeSource":"","RelatedAsset":null,"AssetTraitName":null,"AssetTraitValue":null,"Fingerprint":"4v8eqarkd7","Integrity":"YJa7W8EiQdQpkk93iGEjjnLSUWRpRJbSfzfURh1kxz4=","CopyToOutputDirectory":"Never","CopyToPublishDirectory":"PreserveNewest","OriginalItemSpec":"wwwroot\\lib\\jquery-validation-unobtrusive\\jquery.validate.unobtrusive.min.js","FileLength":5824,"LastWriteTime":"2025-11-21T06:19:08.8247063+00:00"},"pClhH5MNBBHyi56KPbc\u002BdHFekLF/KnWrIjcXBLbE724=":{"Identity":"D:\\saranya\\Job search\\HoneyWell\\VideoMediaApp\\wwwroot\\lib\\jquery-validation-unobtrusive\\LICENSE.txt","SourceId":"VideoMediaApp","SourceType":"Discovered","ContentRoot":"D:\\saranya\\Job search\\HoneyWell\\VideoMediaApp\\wwwroot\\","BasePath":"_content/VideoMediaApp","RelativePath":"lib/jquery-validation-unobtrusive/LICENSE#[.{fingerprint}]?.txt","AssetKind":"All","AssetMode":"All","AssetRole":"Primary","AssetMergeBehavior":null,"AssetMergeSource":"","RelatedAsset":null,"AssetTraitName":null,"AssetTraitValue":null,"Fingerprint":"356vix0kms","Integrity":"16aFlqtpsG9RyieKZUUUjkJpqTgcJtWXwT312I4Iz1s=","CopyToOutputDirectory":"Never","CopyToPublishDirectory":"PreserveNewest","OriginalItemSpec":"wwwroot\\lib\\jquery-validation-unobtrusive\\LICENSE.txt","FileLength":1139,"LastWriteTime":"2025-11-21T06:19:08.9032184+00:00"},"XLNBTR/0hC8ZlHHXKvWb6jc1ZEbl2rVWQPrcG2aWmWQ=":{"Identity":"D:\\saranya\\Job search\\HoneyWell\\VideoMediaApp\\wwwroot\\lib\\jquery-validation\\dist\\additional-methods.js","SourceId":"VideoMediaApp","SourceType":"Discovered","ContentRoot":"D:\\saranya\\Job search\\HoneyWell\\VideoMediaApp\\wwwroot\\","BasePath":"_content/VideoMediaApp","RelativePath":"lib/jquery-validation/dist/additional-methods#[.{fingerprint}]?.js","AssetKind":"All","AssetMode":"All","AssetRole":"Primary","AssetMergeBehavior":null,"AssetMergeSource":"","RelatedAsset":null,"AssetTraitName":null,"AssetTraitValue":null,"Fingerprint":"ay5nd8zt9x","Integrity":"4jrcLBsi0Ugm8iLKdqDsAyaCDjkscYZdoGuNH/zqs4E=","CopyToOutputDirectory":"Never","CopyToPublishDirectory":"PreserveNewest","OriginalItemSpec":"wwwroot\\lib\\jquery-validation\\dist\\additional-methods.js","FileLength":52977,"LastWriteTime":"2025-11-21T06:19:07.3652365+00:00"},"IWFTt8tKWtZUZebHoAisEmkTwR9uW84G2FHZR5pYZC4=":{"Identity":"D:\\saranya\\Job search\\HoneyWell\\VideoMediaApp\\wwwroot\\lib\\jquery-validation\\dist\\additional-methods.min.js","SourceId":"VideoMediaApp","SourceType":"Discovered","ContentRoot":"D:\\saranya\\Job search\\HoneyWell\\VideoMediaApp\\wwwroot\\","BasePath":"_content/VideoMediaApp","RelativePath":"lib/jquery-validation/dist/additional-methods.min#[.{fingerprint}]?.js","AssetKind":"All","AssetMode":"All","AssetRole":"Primary","AssetMergeBehavior":null,"AssetMergeSource":"","RelatedAsset":null,"AssetTraitName":null,"AssetTraitValue":null,"Fingerprint":"9oaff4kq20","Integrity":"N11IyJpHTgDcSCb3AfX4VrBnpGQeem1NoNzzgcXVyCc=","CopyToOutputDirectory":"Never","CopyToPublishDirectory":"PreserveNewest","OriginalItemSpec":"wwwroot\\lib\\jquery-validation\\dist\\additional-methods.min.js","FileLength":22177,"LastWriteTime":"2025-11-21T06:19:07.4077212+00:00"},"cs6JyLI4pdxMgP0oam2IkabpyXkdItxW51bntV0z6Ac=":{"Identity":"D:\\saranya\\Job search\\HoneyWell\\VideoMediaApp\\wwwroot\\lib\\jquery-validation\\dist\\jquery.validate.js","SourceId":"VideoMediaApp","SourceType":"Discovered","ContentRoot":"D:\\saranya\\Job search\\HoneyWell\\VideoMediaApp\\wwwroot\\","BasePath":"_content/VideoMediaApp","RelativePath":"lib/jquery-validation/dist/jquery.validate#[.{fingerprint}]?.js","AssetKind":"All","AssetMode":"All","AssetRole":"Primary","AssetMergeBehavior":null,"AssetMergeSource":"","RelatedAsset":null,"AssetTraitName":null,"AssetTraitValue":null,"Fingerprint":"pzqfkb6aqo","Integrity":"m0l81WDPiG7CcG7CDsTuZzvcGvyFmrQY5DLIxx3aRGw=","CopyToOutputDirectory":"Never","CopyToPublishDirectory":"PreserveNewest","OriginalItemSpec":"wwwroot\\lib\\jquery-validation\\dist\\jquery.validate.js","FileLength":51171,"LastWriteTime":"2025-11-21T06:19:07.4234024+00:00"},"Z92dQ1U90JZNYW\u002BPiX323NHgAX3gicImS3gkY640nbA=":{"Identity":"D:\\saranya\\Job search\\HoneyWell\\VideoMediaApp\\wwwroot\\lib\\jquery-validation\\dist\\jquery.validate.min.js","SourceId":"VideoMediaApp","SourceType":"Discovered","ContentRoot":"D:\\saranya\\Job search\\HoneyWell\\VideoMediaApp\\wwwroot\\","BasePath":"_content/VideoMediaApp","RelativePath":"lib/jquery-validation/dist/jquery.validate.min#[.{fingerprint}]?.js","AssetKind":"All","AssetMode":"All","AssetRole":"Primary","AssetMergeBehavior":null,"AssetMergeSource":"","RelatedAsset":null,"AssetTraitName":null,"AssetTraitValue":null,"Fingerprint":"b7iojwaux1","Integrity":"JwUksNJ6/R07ZiLRoXbGeNrtlFZMFDKX4hemPiHOmCA=","CopyToOutputDirectory":"Never","CopyToPublishDirectory":"PreserveNewest","OriginalItemSpec":"wwwroot\\lib\\jquery-validation\\dist\\jquery.validate.min.js","FileLength":24601,"LastWriteTime":"2025-11-21T06:19:07.455515+00:00"},"6xiJtNf\u002BEnaZull9ip/rrDrtrnwM\u002BLEM/PSA81naWls=":{"Identity":"D:\\saranya\\Job search\\HoneyWell\\VideoMediaApp\\wwwroot\\lib\\jquery-validation\\LICENSE.md","SourceId":"VideoMediaApp","SourceType":"Discovered","ContentRoot":"D:\\saranya\\Job search\\HoneyWell\\VideoMediaApp\\wwwroot\\","BasePath":"_content/VideoMediaApp","RelativePath":"lib/jquery-validation/LICENSE#[.{fingerprint}]?.md","AssetKind":"All","AssetMode":"All","AssetRole":"Primary","AssetMergeBehavior":null,"AssetMergeSource":"","RelatedAsset":null,"AssetTraitName":null,"AssetTraitValue":null,"Fingerprint":"x0q3zqp4vz","Integrity":"geHEkw/WGPdaHQMRq5HuNY9snliNzU/y2OW8ycnhGXw=","CopyToOutputDirectory":"Never","CopyToPublishDirectory":"PreserveNewest","OriginalItemSpec":"wwwroot\\lib\\jquery-validation\\LICENSE.md","FileLength":1117,"LastWriteTime":"2025-11-21T06:19:08.6793377+00:00"},"ZEEjR5IV8Ox/vKh0wr9ppDk4vN4M\u002BKYoDFDfCnoq6Rk=":{"Identity":"D:\\saranya\\Job search\\HoneyWell\\VideoMediaApp\\wwwroot\\lib\\jquery\\dist\\jquery.js","SourceId":"VideoMediaApp","SourceType":"Discovered","ContentRoot":"D:\\saranya\\Job search\\HoneyWell\\VideoMediaApp\\wwwroot\\","BasePath":"_content/VideoMediaApp","RelativePath":"lib/jquery/dist/jquery#[.{fingerprint}]?.js","AssetKind":"All","AssetMode":"All","AssetRole":"Primary","AssetMergeBehavior":null,"AssetMergeSource":"","RelatedAsset":null,"AssetTraitName":null,"AssetTraitValue":null,"Fingerprint":"fwhahm2icz","Integrity":"H\u002BK7U5CnXl1h5ywQfKtSj8PCmoN9aaq30gDh27Xc0jk=","CopyToOutputDirectory":"Never","CopyToPublishDirectory":"PreserveNewest","OriginalItemSpec":"wwwroot\\lib\\jquery\\dist\\jquery.js","FileLength":288580,"LastWriteTime":"2025-11-21T06:19:07.1363074+00:00"},"qVivQA9kJJqOlWEiocpKxP5b3An\u002BwH5\u002BXGAUoi7zNgM=":{"Identity":"D:\\saranya\\Job search\\HoneyWell\\VideoMediaApp\\wwwroot\\lib\\jquery\\dist\\jquery.min.js","SourceId":"VideoMediaApp","SourceType":"Discovered","ContentRoot":"D:\\saranya\\Job search\\HoneyWell\\VideoMediaApp\\wwwroot\\","BasePath":"_content/VideoMediaApp","RelativePath":"lib/jquery/dist/jquery.min#[.{fingerprint}]?.js","AssetKind":"All","AssetMode":"All","AssetRole":"Primary","AssetMergeBehavior":null,"AssetMergeSource":"","RelatedAsset":null,"AssetTraitName":null,"AssetTraitValue":null,"Fingerprint":"dd6z7egasc","Integrity":"/xUj\u002B3OJU5yExlq6GSYGSHk7tPXikynS7ogEvDej/m4=","CopyToOutputDirectory":"Never","CopyToPublishDirectory":"PreserveNewest","OriginalItemSpec":"wwwroot\\lib\\jquery\\dist\\jquery.min.js","FileLength":89501,"LastWriteTime":"2025-11-21T06:19:07.2523623+00:00"},"ti6e3lwvJqReCSSogjPI4NQUvH9IZUqaj0XQQtxyhDY=":{"Identity":"D:\\saranya\\Job search\\HoneyWell\\VideoMediaApp\\wwwroot\\lib\\jquery\\dist\\jquery.min.map","SourceId":"VideoMediaApp","SourceType":"Discovered","ContentRoot":"D:\\saranya\\Job search\\HoneyWell\\VideoMediaApp\\wwwroot\\","BasePath":"_content/VideoMediaApp","RelativePath":"lib/jquery/dist/jquery.min#[.{fingerprint}]?.map","AssetKind":"All","AssetMode":"All","AssetRole":"Primary","AssetMergeBehavior":null,"AssetMergeSource":"","RelatedAsset":null,"AssetTraitName":null,"AssetTraitValue":null,"Fingerprint":"5pze98is44","Integrity":"OZVI\u002Bw57FGwS9boYCZpH1ZSpcP7pYhLu4KtIUvPlZ4I=","CopyToOutputDirectory":"Never","CopyToPublishDirectory":"PreserveNewest","OriginalItemSpec":"wwwroot\\lib\\jquery\\dist\\jquery.min.map","FileLength":137972,"LastWriteTime":"2025-11-21T06:19:07.3410226+00:00"},"gK9tVigDW17E/Z7n5K9ExM2gVwDH2cSfnrzK8um2xWo=":{"Identity":"D:\\saranya\\Job search\\HoneyWell\\VideoMediaApp\\wwwroot\\lib\\jquery\\LICENSE.txt","SourceId":"VideoMediaApp","SourceType":"Discovered","ContentRoot":"D:\\saranya\\Job search\\HoneyWell\\VideoMediaApp\\wwwroot\\","BasePath":"_content/VideoMediaApp","RelativePath":"lib/jquery/LICENSE#[.{fingerprint}]?.txt","AssetKind":"All","AssetMode":"All","AssetRole":"Primary","AssetMergeBehavior":null,"AssetMergeSource":"","RelatedAsset":null,"AssetTraitName":null,"AssetTraitValue":null,"Fingerprint":"mlv21k5csn","Integrity":"hjIBkvmgxQXbNXK3B9YQ3t06RwLuQSQzC/dpvuB/lMk=","CopyToOutputDirectory":"Never","CopyToPublishDirectory":"PreserveNewest","OriginalItemSpec":"wwwroot\\lib\\jquery\\LICENSE.txt","FileLength":1117,"LastWriteTime":"2025-11-21T06:19:08.6491406+00:00"},"hSJZfVJjHPh1RloJkFJWDjMpSpLJPgCb2OTppjgK0zk=":{"Identity":"D:\\saranya\\Job search\\HoneyWell\\VideoMediaApp\\wwwroot\\media\\BRUSH BRUSH BRUSH YOUR TEETH - Animated Rhymes.flv.mp4","SourceId":"VideoMediaApp","SourceType":"Discovered","ContentRoot":"D:\\saranya\\Job search\\HoneyWell\\VideoMediaApp\\wwwroot\\","BasePath":"_content/VideoMediaApp","RelativePath":"media/BRUSH BRUSH BRUSH YOUR TEETH - Animated Rhymes.flv#[.{fingerprint}]?.mp4","AssetKind":"All","AssetMode":"All","AssetRole":"Primary","AssetMergeBehavior":null,"AssetMergeSource":"","RelatedAsset":null,"AssetTraitName":null,"AssetTraitValue":null,"Fingerprint":"fi0g29iui7","Integrity":"afOooLrg2uHOry3/TxAkHs2xhYOLjrbul2WxHR9jCTs=","CopyToOutputDirectory":"Never","CopyToPublishDirectory":"PreserveNewest","OriginalItemSpec":"wwwroot\\media\\BRUSH BRUSH BRUSH YOUR TEETH - Animated Rhymes.flv.mp4","FileLength":6100267,"LastWriteTime":"2025-11-24T03:41:46.7944641+00:00"}},"CachedCopyCandidates":{}}